{
  "$schema": "http://json-schema.org/draft-04/schema#",
  "type": "object",
  "title": "LinkedContentEntry",
  "additionalProperties": false,
  "properties": {
    "hasMin": {
      "type": "boolean"
    },
    "dependencies": {
      "type": [
        "array",
        "null"
      ],
      "items": {
        "type": "string"
      }
    },
    "css": {
      "type": [
        "array",
        "null"
      ],
      "items": {
        "type": "string"
      }
    },
    "js": {
      "type": [
        "array",
        "null"
      ],
      "items": {
        "$ref": "#/definitions/JavascriptEntry"
      }
    }
  },
  "definitions": {
    "JavascriptEntry": {
      "type": "object",
      "additionalProperties": false,
      "properties": {
        "file": {
          "type": [
            "null",
            "string"
          ]
        },
        "async": {
          "type": "boolean"
        }
      }
    }
  }
}